.gitignore
LICENSE.txt
MANIFEST.in
README.md
pyproject.toml
setup.py
.github/workflows/python-publish.yml
.github/workflows/python_build_macos.yml
qimview/__init__.py
qimview/imview.py
qimview/mview.py
qimview/npViewer.py
qimview.egg-info/PKG-INFO
qimview.egg-info/SOURCES.txt
qimview.egg-info/dependency_links.txt
qimview.egg-info/entry_points.txt
qimview.egg-info/requires.txt
qimview.egg-info/top_level.txt
qimview/cache/__init__.py
qimview/cache/basecache.py
qimview/cache/filecache.py
qimview/cache/imagecache.py
qimview/cpp_bind/.gitignore
qimview/cpp_bind/CMakeLists.txt
qimview/cpp_bind/image_histogram.hpp
qimview/cpp_bind/image_resize.hpp
qimview/cpp_bind/image_to_rgb.hpp
qimview/cpp_bind/qimview_cpp.cpp
qimview/cpp_bind/test_speed.py
qimview/cpp_bind/test_speed_resize.py
qimview/ffmpeg_cpp/CMakeLists.txt
qimview/ffmpeg_cpp/README.txt
qimview/ffmpeg_cpp/decode_video.cpp
qimview/ffmpeg_cpp/decode_video.hpp
qimview/ffmpeg_cpp/decode_video.pybind.cpp
qimview/ffmpeg_cpp/decode_video_main.cpp
qimview/ffmpeg_cpp/test_video_player.py
qimview/ffmpeg_cpp/cmake/FindFFMPEG.cmake
qimview/image_readers/__init__.py
qimview/image_readers/image_reader.py
qimview/image_readers/libraw_reader.py
qimview/image_readers/opencv_reader.py
qimview/image_readers/simplejpeg_reader.py
qimview/image_readers/turbojpeg_reader.py
qimview/image_viewers/__init__.py
qimview/image_viewers/fullscreen_helper.py
qimview/image_viewers/gl_image_viewer.py
qimview/image_viewers/gl_image_viewer_base.py
qimview/image_viewers/gl_image_viewer_shaders.py
qimview/image_viewers/gltexture.py
qimview/image_viewers/image_filter_parameters.py
qimview/image_viewers/image_filter_parameters_gui.py
qimview/image_viewers/image_viewer.py
qimview/image_viewers/image_viewer_key_events.py
qimview/image_viewers/image_viewer_mouse_events.py
qimview/image_viewers/mouse_events.py
qimview/image_viewers/multi_view.py
qimview/image_viewers/multi_view_key_events.py
qimview/image_viewers/multi_view_mouse_events.py
qimview/image_viewers/qt_image_viewer.py
qimview/parameters/__init__.py
qimview/parameters/numeric_parameter.py
qimview/parameters/numeric_parameter_gui.py
qimview/pytests/tutorial/test_div_by_3_6.py
